datetime_lib/__init__.py
datetime_lib/__main__.py
datetime_lib/core.py
datetimelib-0.1.0.dist-info/licenses/LICENSE
datetimelib-0.1.0.dist-info/METADATA
datetimelib-0.1.0.dist-info/WHEEL
datetimelib-0.1.0.dist-info/entry_points.txt
datetimelib-0.1.0.dist-info/top_level.txt
datetimelib-0.1.0.dist-info/RECORD
