Metadata-Version: 2.4
Name: DateTimeLib
Version: 0.1.0
Summary: Library to get current date and time
Author: Adel Amin Alashmouri
Author-email: Adel Amin Alashmouri <ashmouri12ty@gmail.com>
License: MIT License
Project-URL: Homepage, https://pypi.org/project/DateTimeLib/
Requires-Python: >=3.7
License-File: LICENSE
Dynamic: author
Dynamic: license-file
Dynamic: requires-python
